LICENSE
README.md
setup.py
JanexPT/__init__.py
JanexPT/chat.py
JanexPT/main.py
JanexPT/train.py
JanexPT.egg-info/PKG-INFO
JanexPT.egg-info/SOURCES.txt
JanexPT.egg-info/dependency_links.txt
JanexPT.egg-info/requires.txt
JanexPT.egg-info/top_level.txt
JanexPT/JanexSub/JanexSub.py
JanexPT/JanexSub/__init__.py