Metadata-Version: 2.1
Name: JanexPT
Version: 0.0.45
Home-page: https://github.com/Cipher58/Janex-Pytorch
Download-URL: https://github.com/Cipher58/Janex-Pytorch
Author: Cipher58
Author-email: cipher58public@gmail.com
License: Lily 1.0
Classifier: Programming Language :: Python :: 3
Classifier: Operating System :: OS Independent
License-File: LICENSE
